plicat_model/__init__.py
plicat_model/configuration_plicat.py
plicat_model/modeling_plicat.py
plicat_model-0.1.0.dist-info/METADATA
plicat_model-0.1.0.dist-info/WHEEL
plicat_model-0.1.0.dist-info/top_level.txt
plicat_model-0.1.0.dist-info/RECORD
