Metadata-Version: 2.4
Name: plicat_model
Version: 0.1.0
Summary: A custom PLiCat model for lipid-binding Protein prediction
Home-page: https://huggingface.co/Noora68/PLiCat-0.4B
Author: FeitongDong
Author-email: 12031011@mail.sustech.edu.cn
License: MIT
Classifier: Programming Language :: Python :: 3
Classifier: License :: OSI Approved :: MIT License
Classifier: Operating System :: OS Independent
Requires-Python: >=3.8
Requires-Dist: torch>=2.7.0
Requires-Dist: transformers>=4.32.0
Requires-Dist: esm>=0.5.0
Dynamic: author
Dynamic: author-email
Dynamic: classifier
Dynamic: description
Dynamic: description-content-type
Dynamic: home-page
Dynamic: license
Dynamic: requires-dist
Dynamic: requires-python
Dynamic: summary
